pymilvus_orm/__init__.py
pymilvus_orm/collection.py
pymilvus_orm/connections.py
pymilvus_orm/constants.py
pymilvus_orm/default_config.py
pymilvus_orm/exceptions.py
pymilvus_orm/index.py
pymilvus_orm/partition.py
pymilvus_orm/prepare.py
pymilvus_orm/schema.py
pymilvus_orm/search.py
pymilvus_orm/types.py
pymilvus_orm/utility.py
pymilvus_orm-0.0.1.dist-info/METADATA
pymilvus_orm-0.0.1.dist-info/WHEEL
pymilvus_orm-0.0.1.dist-info/top_level.txt
pymilvus_orm-0.0.1.dist-info/RECORD
