Metadata-Version: 2.1
Name: pymilvus-orm
Version: 0.0.1
Summary: Python ORM Sdk for Milvus(>= 2.0)
Home-page: https://github.com/milvus-io/pymilvus-orm.git
License: Apache-2.0
Platform: UNKNOWN
Classifier: Programming Language :: Python :: 3.6
Classifier: Programming Language :: Python :: 3.7
Classifier: Programming Language :: Python :: 3.8
Requires-Python: >=3.6
Requires-Dist: requests (==2.22.0)
Requires-Dist: requests-toolbelt (==0.9.1)
Requires-Dist: pymilvus-distributed (==0.0.63)
Requires-Dist: m2r (==0.2.1)
Requires-Dist: pandas
Requires-Dist: numpy
Requires-Dist: sklearn (==0.0)
Requires-Dist: Sphinx (==2.3.1)
Requires-Dist: sphinx-copybutton (==0.3.1)
Requires-Dist: sphinx-rtd-theme (==0.4.3)
Requires-Dist: sphinxcontrib-applehelp (==1.0.1)
Requires-Dist: sphinxcontrib-devhelp (==1.0.1)
Requires-Dist: sphinxcontrib-htmlhelp (==1.0.2)
Requires-Dist: sphinxcontrib-jsmath (==1.0.1)
Requires-Dist: sphinxcontrib-qthelp (==1.0.2)
Requires-Dist: sphinxcontrib-serializinghtml (==1.1.3)
Requires-Dist: pytest (==5.3.4)
Requires-Dist: pytest-cov (==2.8.1)
Requires-Dist: pytest-timeout (==1.3.4)
